{
  "image_path": "tomato_training_project\\raw_images\\tomato_detection\\0255.JPG",
  "image_name": "0255.JPG",
  "task": "tomato_detection",
  "annotations": [
    {
      "class": "tomato",
      "bbox": [
        3109.0,
        1565.0,
        3761.0,
        2077.0
      ],
      "width": 4032,
      "height": 3024
    },
    {
      "class": "tomato",
      "bbox": [
        2066.0,
        1698.0,
        2650.0,
        2276.0
      ],
      "width": 4032,
      "height": 3024
    },
    {
      "class": "tomato",
      "bbox": [
        2792.0,
        956.0,
        3583.0,
        1715.0
      ],
      "width": 4032,
      "height": 3024
    },
    {
      "class": "tomato",
      "bbox": [
        1246.0,
        1337.0,
        2244.0,
        2265.0
      ],
      "width": 4032,
      "height": 3024
    },
    {
      "class": "tomato",
      "bbox": [
        1328.0,
        457.0,
        2067.0,
        1092.0
      ],
      "width": 4032,
      "height": 3024
    },
    {
      "class": "tomato",
      "bbox": [
        952.0,
        1874.0,
        1686.0,
        2566.0
      ],
      "width": 4032,
      "height": 3024
    },
    {
      "class": "tomato",
      "bbox": [
        2422.0,
        1830.0,
        3702.0,
        2935.0
      ],
      "width": 4032,
      "height": 3024
    }
  ],
  "labeled_date": "2025-08-23T20:48:31.374012"
}